pyleapo/__init__.py
pyleapo/aio.py
pyleapo/history.py
pyleapo/overview.py
pyleapo-1.0.3.dist-info/LICENSE
pyleapo-1.0.3.dist-info/METADATA
pyleapo-1.0.3.dist-info/WHEEL
pyleapo-1.0.3.dist-info/top_level.txt
pyleapo-1.0.3.dist-info/RECORD
