Metadata-Version: 2.1
Name: pyleapo
Version: 1.0.3
Summary: A Python API for accessing your Leap Card balance, overview, and travel credit history.
Home-page: https://github.com/zanaaziz/pyleapo
Author: Zana Aziz
Author-email: mail@zanaaziz.com
License: MIT
Keywords: leap card leapcard api ireland zana
Platform: UNKNOWN
Classifier: Programming Language :: Python :: 3.5
Classifier: License :: OSI Approved :: MIT License
Classifier: Operating System :: OS Independent
Requires-Python: >=3.5.2
Requires-Dist: Scrapy (>=2.2.1)
Requires-Dist: scrapy-user-agents (>=0.1.1)
